README.md
setup.py
bisip/GUI.py
bisip/__init__.py
bisip/call_BISIP.py
bisip/cython_funcs.pyx
bisip/cython_setup.py
bisip/hook-numpy.py
bisip/invResults.py
bisip/models.py
bisip.egg-info/PKG-INFO
bisip.egg-info/SOURCES.txt
bisip.egg-info/dependency_links.txt
bisip.egg-info/requires.txt
bisip.egg-info/top_level.txt