Metadata-Version: 1.0
Name: bisip
Version: 0.0.4
Summary: Bayesian inversion of SIP data
Home-page: https://github.com/clberube/BISIP
Author: Charles L. Berube
Author-email: cberube@ageophysics.com
License: MIT
Keywords: testing,logging,example
Platform: UNKNOWN
